m3u8_XZ/__init__.py
m3u8_XZ/cryptoModel.py
m3u8_XZ/xz.py
m3u8_XZ-0.0.14.dist-info/LICENSE
m3u8_XZ-0.0.14.dist-info/METADATA
m3u8_XZ-0.0.14.dist-info/WHEEL
m3u8_XZ-0.0.14.dist-info/top_level.txt
m3u8_XZ-0.0.14.dist-info/RECORD
