Metadata-Version: 2.1
Name: m3u8_XZ
Version: 0.0.14
Summary: download m3u8 video by m3u8 url or by local m3u8 file.
Author: XZ
Author-email: 345841407@qq.com
Classifier: Programming Language :: Python :: 3
Classifier: License :: OSI Approved :: MIT License
Classifier: Operating System :: OS Independent
License-File: LICENSE
Requires-Dist: requests
Requires-Dist: aiohttp
Requires-Dist: pycryptodome
